README.md
setup.py
web/__init__.py
web/application.py
web/browser.py
web/db.py
web/debugerror.py
web/form.py
web/http.py
web/httpserver.py
web/net.py
web/py3helpers.py
web/session.py
web/template.py
web/test.py
web/utils.py
web/webapi.py
web/webopenid.py
web/wsgi.py
web/contrib/__init__.py
web/contrib/template.py
web/wsgiserver/__init__.py
web/wsgiserver/ssl_builtin.py
web/wsgiserver/ssl_pyopenssl.py
web/wsgiserver/wsgiserver2.py
web/wsgiserver/wsgiserver3.py
webpy3legacysupport.egg-info/PKG-INFO
webpy3legacysupport.egg-info/SOURCES.txt
webpy3legacysupport.egg-info/dependency_links.txt
webpy3legacysupport.egg-info/top_level.txt