Metadata-Version: 1.0
Name: webpy3legacysupport
Version: 0.0.1
Summary: web.py: makes web apps
Home-page: https://github.com/webpy/webpy
Author: Anand Chitipothu
Author-email: anandology@gmail.com
License: Public domain
Platform: any
